kdrive_upload/__init__.py
kdrive_upload/__main__.py
kdrive_upload/kdrive.py
kdrive_upload/kdrive_test.py
kdrive_upload-0.6.1.dist-info/LICENSE
kdrive_upload-0.6.1.dist-info/METADATA
kdrive_upload-0.6.1.dist-info/WHEEL
kdrive_upload-0.6.1.dist-info/entry_points.txt
kdrive_upload-0.6.1.dist-info/top_level.txt
kdrive_upload-0.6.1.dist-info/RECORD
