Metadata-Version: 2.1
Name: kdrive-upload
Version: 0.6.1
Summary: Upload files to kDrive
Home-page: UNKNOWN
Author: Rene Luria
Author-email: rene.luria@infomaniak.com
License: UNKNOWN
Platform: UNKNOWN
Requires-Dist: webdavclient3
